lowvision/__init__.py
lowvision/chat.py
lowvision/chat_mode_trigger.py
lowvision/shell.py
lowvision-0.3.0.dist-info/METADATA
lowvision-0.3.0.dist-info/WHEEL
lowvision-0.3.0.dist-info/entry_points.txt
lowvision-0.3.0.dist-info/top_level.txt
lowvision-0.3.0.dist-info/RECORD
