Metadata-Version: 2.1
Name: lowvision
Version: 0.3.0
Summary: Tools for low-vision coders
Author-email: Daniel Cox <danielpcox@gmail.com>
Requires-Python: >=3.9
Requires-Dist: openai
